czyMysql.py
setup.py
czyMysql.egg-info/PKG-INFO
czyMysql.egg-info/SOURCES.txt
czyMysql.egg-info/dependency_links.txt
czyMysql.egg-info/top_level.txt