Metadata-Version: 1.0
Name: czyMysql
Version: 1.0
Summary: mysql连接优化
Home-page: https://www.cnblogs.com/RainBol/
Author: RainBol
Author-email: 2497643794@qq.com
License: UNKNOWN
Platform: UNKNOWN
